articlang/__init__.py
articlang/article_lang.py
asrticlang-1.0.0.dist-info/LICENSE
asrticlang-1.0.0.dist-info/METADATA
asrticlang-1.0.0.dist-info/WHEEL
asrticlang-1.0.0.dist-info/top_level.txt
asrticlang-1.0.0.dist-info/RECORD
