Metadata-Version: 2.1
Name: asrticlang
Version: 1.0.0
Summary: Investigate the language ratio of the latest articles of Qiita.
Home-page: https://github.com/RyotaKITA-12/articlang
Download-URL: https://github.com/RyotaKITA-12/articlang
Author: KITA Ryota
Author-email: kita.h131212@gmail.com
Maintainer: KITA Ryota
Maintainer-email: kita.h131212@gmail.com
License: MIT
Keywords: qiita language graph
Platform: UNKNOWN
Classifier: License :: OSI Approved :: MIT License
Classifier: Programming Language :: Python :: 3.6
License-File: LICENSE
Requires-Dist: beautifulsoup4 (==4.11.1)
Requires-Dist: matplotlib (==3.5.2)
Requires-Dist: requests (==2.27.1)
Requires-Dist: setuptools (==49.2.1)
